README.rst
setup.py
src/sdh/__init__.py
src/sdh.dbutils.egg-info/PKG-INFO
src/sdh.dbutils.egg-info/SOURCES.txt
src/sdh.dbutils.egg-info/dependency_links.txt
src/sdh.dbutils.egg-info/eager_resources.txt
src/sdh.dbutils.egg-info/namespace_packages.txt
src/sdh.dbutils.egg-info/not-zip-safe
src/sdh.dbutils.egg-info/top_level.txt
src/sdh/dbutils/__init__.py
src/sdh/dbutils/diff.py
src/sdh/dbutils/shortcut.py
src/sdh/dbutils/sql.py