Metadata-Version: 1.1
Name: sdh.dbutils
Version: 0.1.0
Summary: Database helpers
Home-page: https://sdh.com.ua/
Author: Software Development Hub LLC
Author-email: dev-tools@sdh.com.ua
License: BSD
Platform: UNKNOWN
Classifier: Development Status :: 3 - Alpha
Classifier: Intended Audience :: Developers
Classifier: License :: OSI Approved :: BSD License
Classifier: Operating System :: OS Independent
Classifier: Programming Language :: Python
Classifier: Programming Language :: Python :: 2
Classifier: Programming Language :: Python :: 2.7
Classifier: Programming Language :: Python :: 3
Classifier: Programming Language :: Python :: 3.6
Classifier: Topic :: Software Development :: Libraries :: Python Modules
